Workbook

Sheet Welcome
B2: AI Readiness Discovery
B3: Based on the SPARK framework — for Small & Medium Businesses
B6: About this discovery
B7: A 15-minute guided check-in. Run it 1-on-1 with an advisor, or fill it in
B8: yourself before your advisor meeting.
B10: By the end you'll have:
B11: • An overall AI Readiness score (0–100%) with a band
B12: • A breakdown across the 5 SPARK steps
B13: • Your Top 3 Pain Points (Leaks) — where AI can help most
B14: • Detail on your top 2 pains, including grant-screening data
B15: • Your suggested next step
B18: How to use
... B30: Continue → the 'Questionnaire' tab

Sheet Questionnaire
B2: AI Readiness Discovery — Questionnaire
B3: Fill in Parts 1–5. Results auto-calculate in 'Your Results' tab.
K6: Customer communication | L6: =$C$42 -> 0 | M6: =IFERROR(L6-ROW()/1000,0) -> -0.006
B7: PART 1 OF 6 | K7: Sales & quotes | L7: =$C$44 -> 0 | M7: =IFERROR(L7-ROW()/1000,0) -> -0.007
B8: Business basics | K8: Admin & paperwork | L8: =$C$46 -> 0 | M8: =IFERROR(L8-ROW()/1000,0) -> -0.008
K9: Content & marketing | L9: =$C$48 -> 0 | M9: =IFERROR(L9-ROW()/1000,0) -> -0.009
B10: Business name | K10: Meetings & notes | L10: =$C$50 -> 0 | M10: =IFERROR(L10-ROW()/1000,0) -> -0.01
B11: UEN | K11: Data work | L11: =$C$52 -> 0 | M11: =IFERROR(L11-ROW()/1000,0) -> -0.011
B12: Contact number | K12: People & onboarding | L12: =$C$54 -> 0 | M12: =IFERROR(L12-ROW()/1000,0) -> -0.012
B13: Email address | K13: Knowledge & docs | L13: =$C$56 -> 0 | M13: =IFERROR(L13-ROW()/1000,0) -> -0.013
B14: Industry | D14: Dropdown — F&B, Retail, etc.
B15: Total employees | D15: Dropdown — band
B16: Local employees | D16: Number
B17: Foreign employees | D17: Number
B18: Advisor name
B21: PART 2 OF 6
B22: AI Readiness — rate 1 (Strongly disagree) to 5 (Strongly agree)
B24: Statement | C24: Rating (1–5) | D24: SPARK step
B25: We know which tasks in our business take up the most time. | D25: S
B26: When work feels slow or repetitive, we stop and ask if there's a better way. | D26: S
B27: We're willing to test a new tool on a small task first. | D27: P
B28: In the last 6 months, we tried something new and it worked. | D28: P
B29: When something works, we write it down so other staff can do it the same way. | D29: A
B30: Every new tool or process has one person in charge. | D30: A
B31: We have a rough idea of how much time each task takes. | D31: R
B32: We check if our tools are actually saving us time or money. | D32: R
B33: Someone in our team keeps up with what's new in technology. | D33: K
B34: We keep improving how we work — not just once and then stop. | D34: K
B38: PART 3 OF 6
B39: Problem Points (Leaks) — rate 1 (Not a problem) to 5 (Major drain)
B41: Pain area | C41: Pain rating (1–5)
B42: Customer communication
B43: Replying to emails and WhatsApp. Same questions again and again. Chasing for replies.
B44: Sales & quotes
B45: Writing quotes and proposals. Replying to enquiries. Putting contracts together.
B46: Admin & paperwork
B47: Invoices. Receipts. Monthly reports. Chasing paperwork.
B48: Content & marketing
B49: Facebook and Instagram posts. Newsletters. Website wording. Flyers.
B50: Meetings & notes
B51: Taking notes. Writing up what was decided. Follow-up emails after.
B52: Data work
B53: Typing the same info in many places. Looking things up. Updating spreadsheets.
... B63: We've auto-identified your top 2 pain points from Part 3. For each one, give us a bit more detail.
B65: #1 Top Pain — auto: | C65: =IFERROR(INDEX(K6:K13,MATCH(LARGE(M6:M13,1),M6:M13,0)),"(complete Part 3)") -> Customer communication | D65: =IFERROR("Pain rating: "&TEXT(LARGE(L6:L13,1),"0")&"/5","") -> Pain rating: 0/5
B66: What does this pain look like in your business?
B67: What are your desired outcomes?
B68: Number of employees affected | D68: Number
B69: Of these, how many are local | D69: Number
B70: Of these, employed > 12 months | D70: Number
B71: Any related to ACRA-listed stakeholders? | D71: Yes / No (family, spouse, kids…)
B73: #2 Top Pain — auto: | C73: =IFERROR(INDEX(K6:K13,MATCH(LARGE(M6:M13,2),M6:M13,0)),"(complete Part 3)") -> Sales & quotes | D73: =IFERROR("Pain rating: "&TEXT(LARGE(L6:L13,2),"0")&"/5","") -> Pain rating: 0/5
B74: What does this pain look like in your business?
B75: What are your desired outcomes?
B76: Number of employees affected | D76: Number
B77: Of these, how many are local | D77: Number
B78: Of these, employed > 12 months | D78: Number
B79: Any related to ACRA-listed stakeholders? | D79: Yes / No (family, spouse, kids…)
B82: PART 5 OF 6
B83: Project logistics
B85: Rough budget for AI | D85: Dropdown
B86: Aware of any of these grants? | D86: Tick Yes for each one you know
B87: • PSG
B88: • EDG
B89: • ECI
B90: • SFEC
B91: Planning new hires? | D91: Yes / No
B92: If yes, how many? | D92: Number
B93: Will you champion this AI project? | D93: Yes / No
B94: If no — Name
B95: If no — Designation
B96: If no — Mobile
B97: If no — Email
B98: Preferred date/time for a 1-on-1 with your advisor
B101: → Open the 'Your Results' tab to see your score, top pain points, and a summary for your advisor.

Sheet Your Results
B2: Your AI Readiness Discovery
B3: Auto-calculated from the Questionnaire tab
B6: Overall AI Readiness
B7: =ROUND(SUM(Questionnaire!C25:C34)/50*100,0)/100 -> 0 | C7: =IF(SUM(Questionnaire!C25:C34)=0,"—",IF(SUM(Questionnaire!C25:C34)/50<0.3,"Just starting",IF(SUM(Questionnaire!C25:C34)/50<0.55,"Getting going",IF(SUM(Questionnaire!C25:C34)/50<0.75,"Building momentum","Well underway")))) -> —
B9: SPARK breakdown
B10: Step | C10: Score | D10: of 10 | E10: What it asks
B11: S — Spot the leaks | C11: =SUM(Questionnaire!C25,Questionnaire!C26) -> 0 | D11: / 10 | E11: Are you systematically finding where time goes?
B12: P — Pilot small wins | C12: =SUM(Questionnaire!C27,Questionnaire!C28) -> 0 | D12: / 10 | E12: Are you willing to test before you commit?
B13: A — Apply what works | C13: =SUM(Questionnaire!C29,Questionnaire!C30) -> 0 | D13: / 10 | E13: Do good ideas turn into team habits?
B14: R — Review results | C14: =SUM(Questionnaire!C31,Questionnaire!C32) -> 0 | D14: / 10 | E14: Are you measuring impact honestly?
B15: K — Keep building | C15: =SUM(Questionnaire!C33,Questionnaire!C34) -> 0 | D15: / 10 | E15: Is improvement a habit, not a project?
B17: Top 3 Pain Points (Leaks)
B18: Rank | C18: Pain area | D18: Pain | E18: Action
B19: #1 | C19: =IFERROR(INDEX(Questionnaire!K6:K13,MATCH(LARGE(Questionnaire!M6:M13,1),Questionnaire!M6:M13,0)),"—") -> Customer communication | D19: =IFERROR(LARGE(Questionnaire!L6:L13,1)&"/5","—") -> 0/5 | E19: Start your pilot here.
B20: #2 | C20: =IFERROR(INDEX(Questionnaire!K6:K13,MATCH(LARGE(Questionnaire!M6:M13,2),Questionnaire!M6:M13,0)),"—") -> Sales & quotes | D20: =IFERROR(LARGE(Questionnaire!L6:L13,2)&"/5","—") -> 0/5 | E20: Save this for your second pilot.
B21: #3 | C21: =IFERROR(INDEX(Questionnaire!K6:K13,MATCH(LARGE(Questionnaire!M6:M13,3),Questionnaire!M6:M13,0)),"—") -> Admin & paperwork | D21: =IFERROR(LARGE(Questionnaire!L6:L13,3)&"/5","—") -> 0/5 | E21: Worth keeping on the list.
B23: Top 2 pain points — your detail
B24: #1 | C24: =Questionnaire!C65 -> Customer communication
B25: What it looks like: | C25: =Questionnaire!C66 -> 0
B26: Desired outcomes: | C26: =Questionnaire!C67 -> 0
B27: Grant-screening: | C27: =IF(Questionnaire!C68="","—",Questionnaire!C68&" affected · "&IF(Questionnaire!C69="","?",Questionnaire!C69)&" local · "&IF(Questionnaire!C70="","?",Questionnaire!C70)&" >12mo · ACRA: "&IF(Questionnaire!C71="","?",Questionnaire!C71)) -> —
B29: #2 | C29: =Questionnaire!C73 -> Sales & quotes
B30: What it looks like: | C30: =Questionnaire!C74 -> 0
B31: Desired outcomes: | C31: =Questionnaire!C75 -> 0
B32: Grant-screening: | C32: =IF(Questionnaire!C76="","—",Questionnaire!C76&" affected · "&IF(Questionnaire!C77="","?",Questionnaire!C77)&" local · "&IF(Questionnaire!C78="","?",Questionnaire!C78)&" >12mo · ACRA: "&IF(Questionnaire!C79="","?",Questionnaire!C79)) -> —
B35: Business & logistics summary
B36: Business name | C36: =IF(Questionnaire!C10="","—",Questionnaire!C10) -> —
B37: UEN | C37: =IF(Questionnaire!C11="","—",Questionnaire!C11) -> —
B38: Contact number | C38: =IF(Questionnaire!C12="","—",Questionnaire!C12) -> —
B39: Email | C39: =IF(Questionnaire!C13="","—",Questionnaire!C13) -> —
B40: Industry | C40: =IF(Questionnaire!C14="","—",Questionnaire!C14) -> —
B41: Total employees | C41: =IF(Questionnaire!C15="","—",Questionnaire!C15) -> —
B42: Local employees | C42: =IF(Questionnaire!C16="","—",Questionnaire!C16) -> —
B43: Foreign employees | C43: =IF(Questionnaire!C17="","—",Questionnaire!C17) -> —
B44: Advisor | C44: =IF(Questionnaire!C18="","—",Questionnaire!C18) -> —
B45: Budget | C45: =IF(Questionnaire!C85="","—",Questionnaire!C85) -> —
B46: Grant awareness — PSG | C46: =IF(Questionnaire!C87="","—",Questionnaire!C87) -> —
B47: Grant awareness — EDG | C47: =IF(Questionnaire!C88="","—",Questionnaire!C88) -> —
B48: Grant awareness — ECI | C48: =IF(Questionnaire!C89="","—",Questionnaire!C89) -> —
B49: Grant awareness — SFEC | C49: =IF(Questionnaire!C90="","—",Questionnaire!C90) -> —
B50: Planning new hires? | C50: =IF(Questionnaire!C91="","—",Questionnaire!C91) -> —
B51: How many? | C51: =IF(Questionnaire!C92="","—",Questionnaire!C92) -> —
B52: Will champion? | C52: =IF(Questionnaire!C93="","—",Questionnaire!C93) -> —
B53: PIC name | C53: =IF(Questionnaire!C94="","—",Questionnaire!C94) -> —
B54: PIC designation | C54: =IF(Questionnaire!C95="","—",Questionnaire!C95) -> —
B55: PIC mobile | C55: =IF(Questionnaire!C96="","—",Questionnaire!C96) -> —
B56: PIC email | C56: =IF(Questionnaire!C97="","—",Questionnaire!C97) -> —
B57: Preferred 1-on-1 date/time | C57: =IF(Questionnaire!C98="","—",Questionnaire!C98) -> —
B59: Your suggested next step
B60: =IF(SUM(Questionnaire!C25:C34)=0,"Complete Part 2 ratings to get your suggested next step.",IF(SUM(Questionnaire!C25:C34)/50<0.3,"You're early — that's a great place to start. This week: walk your business and list 5–10 painful tasks. Don't solve anything yet. Just see them clearly.",IF(SUM(Questionnaire!C25:C34)/50<0.55,"You have the awareness — now get a quick win. This week: pick your top pain above and run a 2-week pilot with one owner. Keep it small, low-risk, and measurable.",IF(SUM(Questionnaire!C25:C34)/50<0.75,"You're building momentum. This week: turn your best pilot into a one-page playbook so the rest of the team can use it without asking questions.","You're well underway. This week: refresh the leak list, schedule the next 30-day review, and set a small weekly rhythm so improvement keeps compounding.")))) -> Complete Part 2 ratings to get your suggested next step.
